apppy/generic/__init__.py
apppy/generic/encrypt.py
apppy/generic/errors.py
apppy_generic-0.23.2.dist-info/METADATA
apppy_generic-0.23.2.dist-info/WHEEL
apppy_generic-0.23.2.dist-info/RECORD
